betbot/__init__.py
betbot/main.py
betbot/api/ApiConnection.py
betbot/api/Bet.py
betbot/api/Match.py
betbot/api/__init__.py
betbot/data/FootballDataCoUk.py
betbot/data/OddsPortal.py
betbot/data/__init__.py
betbot/prediction/BettingOddsPredictor.py
betbot/prediction/DrawPredictor.py
betbot/prediction/HomeTeamPredictor.py
betbot/prediction/LeagueTablePredictor.py
betbot/prediction/NameAndOddsPredictor.py
betbot/prediction/NamePredictor.py
betbot/prediction/Predictor.py
betbot/prediction/RandomPredictor.py
betbot/prediction/SKLearnPredictor.py
betbot/prediction/__init__.py
betbot/test/__init__.py
betbot-0.7.0.data/scripts/betbot
betbot-0.7.0.data/scripts/multi-betbot
betbot-0.7.0.dist-info/LICENSE
betbot-0.7.0.dist-info/METADATA
betbot-0.7.0.dist-info/WHEEL
betbot-0.7.0.dist-info/top_level.txt
betbot-0.7.0.dist-info/RECORD
