Metadata-Version: 2.1
Name: betbot
Version: 0.7.0
Summary: A betting bot for bundesliga-tippspiel
Home-page: https://gitlab.namibsun.net/namboy94/betbot
Author: Hermann Krumrey
Author-email: hermann@krumreyh.com
License: GNU GPL3
Platform: UNKNOWN
Classifier: License :: OSI Approved :: GNU General Public License v3 (GPLv3)
License-File: LICENSE
Requires-Dist: requests
Requires-Dist: beautifulsoup4
Requires-Dist: puffotter
Requires-Dist: scikit-learn
Requires-Dist: joblib
Requires-Dist: selenium
